netclusterWH/__init__.py
netclusterWH/cli/__init__.py
netclusterWH/cli/client-cli.py
netclusterWH/cli/client_cli.py
netclusterWH/cli/server-cli.py
netclusterWH/cli/server_cli.py
netclusterWH/client/__init__.py
netclusterWH/client/worker.py
netclusterWH/server/__init__.py
netclusterWH/server/server.py
netclusterwh-0.2.1.dist-info/METADATA
netclusterwh-0.2.1.dist-info/WHEEL
netclusterwh-0.2.1.dist-info/entry_points.txt
netclusterwh-0.2.1.dist-info/top_level.txt
netclusterwh-0.2.1.dist-info/RECORD
