Metadata-Version: 2.4
Name: netclusterWH
Version: 0.2.1
Summary: Distributed compute network using WebSockets. Clients are also workers.
Author: Your Name
Requires-Python: >=3.8
Requires-Dist: websockets>=10.0
Dynamic: author
Dynamic: requires-dist
Dynamic: requires-python
Dynamic: summary
